agent_rails-0.3.1.dist-info/METADATA
agent_rails-0.3.1.dist-info/WHEEL
agent_rails-0.3.1.dist-info/entry_points.txt
agent_rails-0.3.1.dist-info/licenses/LICENSE
rails/__init__.py
rails/adapters/__init__.py
rails/adapters/base.py
rails/adapters/langchain.py
rails/adapters/prefect.py
rails/adapters/smolagents.py
rails/conditions.py
rails/core.py
rails/execution.py
rails/injectors.py
rails/lifecycle.py
rails/store.py
rails/types.py
agent_rails-0.3.1.dist-info/RECORD
