Metadata-Version: 2.1
Name: agent-rails
Version: 0.3.1
Summary: put your agents on guardrails
Keywords: ai,agents,lifecycle,management
Author-Email: samjtro <hi@samjtro.com>
License: MIT
Classifier: Development Status :: 3 - Alpha
Classifier: Intended Audience :: Developers
Classifier: License :: OSI Approved :: MIT License
Classifier: Programming Language :: Python :: 3
Classifier: Programming Language :: Python :: 3.11
Classifier: Programming Language :: Python :: 3.12
Classifier: Programming Language :: Python :: 3.13
Classifier: Topic :: Software Development :: Libraries :: Python Modules
Classifier: Topic :: Scientific/Engineering :: Artificial Intelligence
Project-URL: Homepage, https://github.com/rizome-dev/rails
Project-URL: Repository, https://github.com/rizome-dev/rails
Project-URL: Documentation, https://github.com/rizome-dev/rails#readme
Project-URL: Issue Tracker, https://github.com/rizome-dev/rails/issues
Project-URL: Changelog, https://github.com/rizome-dev/rails/blob/main/CHANGELOG.md
Requires-Python: >=3.11
Requires-Dist: pydantic>=2.8.0
Requires-Dist: anyio>=4.4.0
Requires-Dist: typing-extensions>=4.12.0
Requires-Dist: loguru>=0.7.3
Provides-Extra: langchain
Requires-Dist: langchain>=0.1.0; extra == "langchain"
Provides-Extra: smolagents
Requires-Dist: smolagents>=0.1.0; extra == "smolagents"
Provides-Extra: all
Requires-Dist: langchain>=0.1.0; extra == "all"
Requires-Dist: smolagents>=0.1.0; extra == "all"
Provides-Extra: dev
Requires-Dist: pytest>=7.4.0; extra == "dev"
Requires-Dist: pytest-cov>=4.1.0; extra == "dev"
Requires-Dist: pytest-asyncio>=0.21.0; extra == "dev"
Requires-Dist: black>=23.7.0; extra == "dev"
Requires-Dist: isort>=5.12.0; extra == "dev"
Requires-Dist: mypy>=1.5.0; extra == "dev"
Requires-Dist: ruff>=0.0.280; extra == "dev"
Requires-Dist: build>=1.3.0; extra == "dev"
Requires-Dist: twine>=6.1.0; extra == "dev"
